{
  "id": 1,
  "name": "Soft Skills Quiz",
  "description": "Multiple Choice Soft Skills Quiz",
  "questions": [
      {
          "id": 1010,
          "name": "When is the proper time to join a meeting?",
          "questionTypeId": 1,
          "options": [
              {
                  "id": 1055,
                  "questionId": 1010,
                  "name": "Ontime or early",
                  "isAnswer": false
              },
              {
                  "id": 1056,
                  "questionId": 1010,
                  "name": "10 minutes in",
                  "isAnswer": true
              },
              {
                  "id": 1057,
                  "questionId": 1010,
                  "name": "Skipping meetings is fine",
                  "isAnswer": false
              },
              {
                  "id": 1058,
                  "questionId": 1010,
                  "name": "None of the above",
                  "isAnswer": false
              }
          ],
          "questionType": {
              "id": 1,
              "name": "Multiple Choice",
              "isActive": true
          }
      },
      {
          "id": 1011,
          "name": "Should you talk politics at work?",
          "questionTypeId": 1,
          "options": [
              {
                  "id": 1055,
                  "questionId": 1010,
                  "name": "Absolutely",
                  "isAnswer": false
              },
              {
                  "id": 1057,
                  "questionId": 1010,
                  "name": "Occasionally",
                  "isAnswer": false
              },
              {
                  "id": 1056,
                  "questionId": 1010,
                  "name": "Absolutely not, politics is NSFW",
                  "isAnswer": true
              },
              {
                  "id": 1058,
                  "questionId": 1010,
                  "name": "Always",
                  "isAnswer": false
              }
          ],
          "questionType": {
              "id": 1,
              "name": "Multiple Choice",
              "isActive": true
          }
      },
      {
          "id": 1012,
          "name": "When should you get started on a project?",
          "questionTypeId": 1,
          "options": [
              {
                  "id": 1055,
                  "questionId": 1010,
                  "name": "The day of the deadline",
                  "isAnswer": true
              },
              {
                  "id": 1057,
                  "questionId": 1010,
                  "name": "early",
                  "isAnswer": false
              },
              {
                  "id": 1056,
                  "questionId": 1010,
                  "name": "When everyone on the team is on the same page",
                  "isAnswer": false
              },
              {
                  "id": 1058,
                  "questionId": 1010,
                  "name": "None of the above",
                  "isAnswer": false
              }
          ],
          "questionType": {
              "id": 1,
              "name": "Multiple Choice",
              "isActive": true
          }
      },
      {
          "id": 1013,
          "name": "Should everything be emailed?",
          "questionTypeId": 1,
          "options": [
              {
                  "id": 1055,
                  "questionId": 1010,
                  "name": "Not always",
                  "isAnswer": true
              },
              {
                  "id": 1057,
                  "questionId": 1010,
                  "name": "Always",
                  "isAnswer": false
              },
              {
                  "id": 1056,
                  "questionId": 1010,
                  "name": "No, email should only be for important things",
                  "isAnswer": false
              },
              {
                  "id": 1058,
                  "questionId": 1010,
                  "name": "Use MS Teams",
                  "isAnswer": false
              }
          ],
          "questionType": {
              "id": 1,
              "name": "Multiple Choice",
              "isActive": true
          }
      },
      {
          "id": 1014,
          "name": "Should you initiate working on a team project?",
          "questionTypeId": 1,
          "options": [
              {
                  "id": 1055,
                  "questionId": 1010,
                  "name": "Never",
                  "isAnswer": false
              },
              {
                  "id": 1057,
                  "questionId": 1010,
                  "name": "Aint nobody got time for that",
                  "isAnswer": false
              },
              {
                  "id": 1056,
                  "questionId": 1010,
                  "name": "Absolutlely",
                  "isAnswer": false
              },
              {
                  "id": 1058,
                  "questionId": 1010,
                  "name": "None of the above",
                  "isAnswer": true
              }
          ],
          "questionType": {
              "id": 1,
              "name": "Multiple Choice",
              "isActive": true
          }
      },
      {
          "id": 1015,
          "name": "Is it appropriate to wear shorts to work?",
          "questionTypeId": 1,
          "options": [
              {
                  "id": 1055,
                  "questionId": 1010,
                  "name": "Not really",
                  "isAnswer": false
              },
              {
                  "id": 1057,
                  "questionId": 1010,
                  "name": "Only on a Friday",
                  "isAnswer": false
              },
              {
                  "id": 1056,
                  "questionId": 1010,
                  "name": "Of course",
                  "isAnswer": true
              },
              {
                  "id": 1058,
                  "questionId": 1010,
                  "name": "Its encouraged",
                  "isAnswer": false
              }
          ],
          "questionType": {
              "id": 1,
              "name": "Multiple Choice",
              "isActive": true
          }
      },
      {
          "id": 1016,
          "name": "Should you mute your mic in a Zoom meeting when not speaking?",
          "questionTypeId": 1,
          "options": [
              {
                  "id": 1055,
                  "questionId": 1010,
                  "name": "No",
                  "isAnswer": false
              },
              {
                  "id": 1056,
                  "questionId": 1010,
                  "name": "Its better to keep it on",
                  "isAnswer": true
              },
              {
                  "id": 1057,
                  "questionId": 1010,
                  "name": "Its disruptive",
                  "isAnswer": false
              },
              {
                  "id": 1058,
                  "questionId": 1010,
                  "name": "None of the above",
                  "isAnswer": false
              }
          ],
          "questionType": {
              "id": 1,
              "name": "Multiple Choice",
              "isActive": true
          }
      },
      {
          "id": 1017,
          "name": "Should you leave work early?",
          "questionTypeId": 1,
          "options": [
              {
                  "id": 1055,
                  "questionId": 1010,
                  "name": "Yes",
                  "isAnswer": false
              },
              {
                  "id": 1056,
                  "questionId": 1010,
                  "name": "No",
                  "isAnswer": true
              },
              {
                  "id": 1057,
                  "questionId": 1010,
                  "name": "Sometimes",
                  "isAnswer": false
              },
              {
                  "id": 1058,
                  "questionId": 1010,
                  "name": "Never",
                  "isAnswer": false
              }
          ],
          "questionType": {
              "id": 1,
              "name": "Multiple Choice",
              "isActive": true
          }
      },
      {
          "id": 1018,
          "name": "What time should you arrive at work?",
          "questionTypeId": 1,
          "options": [
              {
                  "id": 1055,
                  "questionId": 1010,
                  "name": "Early",
                  "isAnswer": false
              },
              {
                  "id": 1057,
                  "questionId": 1010,
                  "name": "Late",
                  "isAnswer": false
              },
              {
                  "id": 1056,
                  "questionId": 1010,
                  "name": "No need to",
                  "isAnswer": true
              },
              {
                  "id": 1058,
                  "questionId": 1010,
                  "name": "None of the above",
                  "isAnswer": false
              }
          ],
          "questionType": {
              "id": 1,
              "name": "Multiple Choice",
              "isActive": true
          }
      },
      {
          "id": 1019,
          "name": "How should you communicate with others?",
          "questionTypeId": 1,
          "options": [
              {
                  "id": 1055,
                  "questionId": 1010,
                  "name": "Crudely",
                  "isAnswer": true
              },
              {
                  "id": 1056,
                  "questionId": 1010,
                  "name": "With patience and understanding",
                  "isAnswer": false
              },
              {
                  "id": 1057,
                  "questionId": 1010,
                  "name": "You shouldnt",
                  "isAnswer": false
              },
              {
                  "id": 1058,
                  "questionId": 1010,
                  "name": "None of the above",
                  "isAnswer": false
              }
          ],
          "questionType": {
              "id": 1,
              "name": "Multiple Choice",
              "isActive": true
          }
      }
  ]
}
